collie/__init__.py
collie/_version.py
collie/config.py
collie/cross_validation.py
collie/metrics.py
collie/utils.py
collie/interactions/__init__.py
collie/interactions/dataloaders.py
collie/interactions/datasets.py
collie/interactions/samplers.py
collie/loss/__init__.py
collie/loss/bpr.py
collie/loss/hinge.py
collie/loss/metadata_utils.py
collie/loss/warp.py
collie/model/__init__.py
collie/model/cold_start_matrix_factorization.py
collie/model/collaborative_metric_learning.py
collie/model/deep_fm.py
collie/model/hybrid_matrix_factorization.py
collie/model/hybrid_pretrained_matrix_factorization.py
collie/model/matrix_factorization.py
collie/model/mlp_matrix_factorization.py
collie/model/neural_collaborative_filtering.py
collie/model/nonlinear_matrix_factorization.py
collie/model/base/__init__.py
collie/model/base/base_pipeline.py
collie/model/base/layers.py
collie/model/base/multi_stage_pipeline.py
collie/model/base/trainer.py
collie/movielens/__init__.py
collie/movielens/get_data.py
collie/movielens/run.py
collie/movielens/visualize.py
collie-1.3.1.data/data/LICENSE
tests/fixtures/__init__.py
tests/fixtures/cross_validation_fixtures.py
tests/fixtures/interactions_fixtures.py
tests/fixtures/loss_fixtures.py
tests/fixtures/metrics_fixtures.py
tests/fixtures/model_fixtures.py
tests/fixtures/movielens_fixtures.py
tests/fixtures/utils_fixtures.py
collie-1.3.1.dist-info/LICENSE
collie-1.3.1.dist-info/METADATA
collie-1.3.1.dist-info/WHEEL
collie-1.3.1.dist-info/top_level.txt
collie-1.3.1.dist-info/RECORD
