Metadata-Version: 2.1
Name: collie
Version: 1.3.1
Summary: A PyTorch library for preparing, training, and evaluating deep learning hybrid recommender systems.
Home-page: https://github.com/ShopRunner/collie
Download-URL: https://github.com/ShopRunner/collie
Author: Nathan Jones
License: BSD-3-Clause
Project-URL: Documentation, https://collie.readthedocs.io/
Project-URL: Source Code, https://github.com/ShopRunner/collie
Keywords: deep learning,pytorch,recommender
Classifier: Environment :: Console
Classifier: Environment :: GPU
Classifier: Natural Language :: English
Classifier: Development Status :: 4 - Beta
Classifier: Intended Audience :: Developers
Classifier: Topic :: Scientific/Engineering :: Artificial Intelligence
Classifier: License :: OSI Approved :: BSD License
Classifier: Operating System :: OS Independent
Classifier: Programming Language :: Python :: 3
Classifier: Programming Language :: Python :: 3.6
Classifier: Programming Language :: Python :: 3.7
Classifier: Programming Language :: Python :: 3.8
Classifier: Programming Language :: Python :: 3.9
Requires-Python: >=3.6
License-File: LICENSE
Requires-Dist: docstring-parser
Requires-Dist: fire
Requires-Dist: joblib
Requires-Dist: numpy
Requires-Dist: pandas
Requires-Dist: pytorch-lightning (<2.0.0,>=1.0.0)
Requires-Dist: scikit-learn
Requires-Dist: tables
Requires-Dist: torch
Requires-Dist: torchmetrics
Requires-Dist: tqdm
Provides-Extra: dev
Requires-Dist: flake8 ; extra == 'dev'
Requires-Dist: flake8-docstrings ; extra == 'dev'
Requires-Dist: flake8-import-order ; extra == 'dev'
Requires-Dist: importlib-metadata (<5.0) ; extra == 'dev'
Requires-Dist: ipython ; extra == 'dev'
Requires-Dist: ipywidgets ; extra == 'dev'
Requires-Dist: jupyterlab (>=3.0.0) ; extra == 'dev'
Requires-Dist: matplotlib ; extra == 'dev'
Requires-Dist: m2r2 ; extra == 'dev'
Requires-Dist: pip-tools ; extra == 'dev'
Requires-Dist: pydocstyle (<4.0.0) ; extra == 'dev'
Requires-Dist: pytest ; extra == 'dev'
Requires-Dist: pytest-cov (<3.0.0) ; extra == 'dev'
Requires-Dist: sphinx-copybutton ; extra == 'dev'
Requires-Dist: sphinx-rtd-theme (==0.5.2) ; extra == 'dev'
Requires-Dist: widgetsnbextension ; extra == 'dev'
